MANIFEST.in
setup.py
shared.py
PingPung.egg-info/PKG-INFO
PingPung.egg-info/SOURCES.txt
PingPung.egg-info/dependency_links.txt
PingPung.egg-info/entry_points.txt
PingPung.egg-info/top_level.txt
pingpung/__init__.py
pingpung/pingpung.py
pingpung/data/doh.wav
pingpung/data/icon.ico
pingpung/data/play.ico
pingpung/data/woohoo.wav
pingpung/pplib/__init__.py
pingpung/pplib/audio.py
pingpung/pplib/pping.py
pingpung/pplib/pptools.py
pingpung/ppui/about.ui
pingpung/ppui/maingui.ui
pingpung/ppui/pptab.ui