Metadata-Version: 1.1
Name: PingPung
Version: 0.1.14
Summary: Python3/QT4 Multiplatform Ping Application
Home-page: https://github.com/RainDogSoftware/pingpung/
Author: Josh Price
Author-email: Price.JoshuaD@Gmail.com
License: GPLv2
Download-URL: https://github.com/RainDogSoftware/pingpung/tarball/0.1.14
Keywords: ping networking network testing
Platform: UNKNOWN
Classifier: Development Status :: 3 - Alpha
Classifier: Topic :: Utilities
Classifier: License :: OSI Approved :: GNU General Public License v2 (GPLv2)
Classifier: Operating System :: OS Independent
Classifier: Programming Language :: Python :: 3
Classifier: Topic :: Internet
Classifier: Topic :: System :: Networking :: Monitoring
Classifier: Topic :: Utilities
